ssslm/__init__.py
ssslm/__main__.py
ssslm/cli.py
ssslm/model.py
ssslm/ner.py
ssslm/ontology.py
ssslm/py.typed
ssslm/version.py
ssslm/web.py
ssslm-0.1.1.dist-info/licenses/LICENSE
ssslm-0.1.1.dist-info/WHEEL
ssslm-0.1.1.dist-info/entry_points.txt
ssslm-0.1.1.dist-info/METADATA
ssslm-0.1.1.dist-info/RECORD
