Metadata-Version: 2.4
Name: ssslm
Version: 0.1.1
Summary: A simple standard for sharing literal mappings
Keywords: snekpack,cookiecutter
Author: Charles Tapley Hoyt
Author-email: Charles Tapley Hoyt <cthoyt@gmail.com>
License-File: LICENSE
Classifier: Development Status :: 1 - Planning
Classifier: Environment :: Console
Classifier: Intended Audience :: Developers
Classifier: License :: OSI Approved :: MIT License
Classifier: Operating System :: OS Independent
Classifier: Framework :: Pytest
Classifier: Framework :: tox
Classifier: Framework :: Sphinx
Classifier: Natural Language :: English
Classifier: Programming Language :: Python
Classifier: Programming Language :: Python :: 3.10
Classifier: Programming Language :: Python :: 3.11
Classifier: Programming Language :: Python :: 3.12
Classifier: Programming Language :: Python :: 3.13
Classifier: Programming Language :: Python :: 3 :: Only
Classifier: Typing :: Typed
Requires-Dist: curies
Requires-Dist: pydantic
Requires-Dist: pydantic-extra-types[pycountry]
Requires-Dist: tqdm
Requires-Dist: click
Requires-Dist: pystow>=0.7.3
Requires-Dist: gilda ; extra == 'gilda'
Requires-Dist: nltk ; extra == 'gilda'
Requires-Dist: pystow ; extra == 'gilda'
Requires-Dist: boto3 ; extra == 'gilda-default'
Requires-Dist: gilda-slim ; extra == 'gilda-slim'
Requires-Dist: nltk ; extra == 'gilda-slim'
Requires-Dist: pystow ; extra == 'gilda-slim'
Requires-Dist: gliner ; extra == 'gliner'
Requires-Dist: pandas ; extra == 'pandas'
Requires-Dist: spacy ; python_full_version < '3.11' and extra == 'scispacy'
Requires-Dist: scispacy ; python_full_version < '3.11' and extra == 'scispacy'
Requires-Dist: numpy<2.0 ; python_full_version < '3.11' and extra == 'scispacy'
Requires-Dist: fastapi ; extra == 'web'
Requires-Dist: uvicorn ; extra == 'web'
Maintainer: Charles Tapley Hoyt
Maintainer-email: Charles Tapley Hoyt <cthoyt@gmail.com>
Requires-Python: >=3.10
Project-URL: Bug Tracker, https://github.com/cthoyt/ssslm/issues
Project-URL: Documentation, https://ssslm.readthedocs.io
Project-URL: Funding, https://github.com/sponsors/cthoyt
Project-URL: Homepage, https://github.com/cthoyt/ssslm
Project-URL: Repository, https://github.com/cthoyt/ssslm.git
Provides-Extra: gilda
Provides-Extra: gilda-default
Provides-Extra: gilda-slim
Provides-Extra: gliner
Provides-Extra: pandas
Provides-Extra: scispacy
Provides-Extra: web
